ysyx-workbench/npc/shudian/alu/vsrc/alu.v
module alu(
	input [3:0]a,
	input [3:0]b,
	input [2:0]seal,
	output reg [0:0]carry,
	output reg [0:0]overflow,
	output reg [3:0]out);

always @(*)begin
	carry = 1'b0;
	overflow = 1'b0;
	case(seal)
	  3'b000: begin 
			{carry, out} = a + b;
			overflow = ((a[3] == b[3]) && (out[3] != a[3]))? 1'b1:1'b0;
			end
    3'b001: begin
			{carry, out} = a - b;
			if(out[3])
				out = {out[3],~out[2:0]} + 1;
			if ((a[3] != b[3]) && (out[3] != a[3]))
			overflow = 1;
			end
		3'b010: out = ~a;
		3'b011: out = a & b;
		3'b100: out = a | b;
		3'b101: out = a ^ b;
		3'b110: out = (a < b)? 4'b0001:4'b0000;
		3'b111: out = (a == b)? 4'b0001:4'b0000;
		default: begin
						out = 4'b0000;
						carry = 1'b0;
						overflow = 1'b0;
						end
		endcase
	end
endmodule

ysyx-workbench/npc/shudian/alu/dump.vcd
$version Generated by VerilatedVcd $end
$timescale 1s $end

 $scope module TOP $end
  $var wire  4 # a [3:0] $end
  $var wire  4 $ b [3:0] $end
  $var wire  1 & carry [0:0] $end
  $var wire  4 ( out [3:0] $end
  $var wire  1 ' overflow [0:0] $end
  $var wire  3 % seal [2:0] $end
  $scope module alu $end
   $var wire  4 # a [3:0] $end
   $var wire  4 $ b [3:0] $end
   $var wire  1 & carry [0:0] $end
   $var wire  4 ( out [3:0] $end
   $var wire  1 ' overflow [0:0] $end
   $var wire  3 % seal [2:0] $end
  $upscope $end
 $upscope $end
$enddefinitions $end


#1
b0111 #
b0110 $
b001 %
0&
0'
b0001 (
#2
b0011 #
b0001 $
b111 %
b0000 (
#3
b1010 #
b1100 $
b001 %
1&
b1010 (
#4
b1101 #
b1010 $
b011 %
0&
b1000 (
#5
b0010 #
b1011 $
b0010 (
#6
b0110 #
b1100 $
b010 %
b1001 (
#7
b0100 #
b1000 $
b011 %
b0000 (
#8
b1000 #
b0111 $
b101 %
b1111 (
#9
b0110 #
b1010 $
b110 %
b0001 (
#10
b0011 #
b0011 $
b111 %
#11
b1001 #
b1010 $
b110 %
